tsv2sqlite/__init__.py
tsv2sqlite/add_header_row.py
tsv2sqlite/csv2sqlite.py
tsv2sqlite/file_utils.py
tsv2sqlite/main.py
tsv2sqlite/manager.py
tsv2sqlite/sqlite3_utils.py
tsv2sqlite/conf/config.yaml
tsv2sqlite-0.5.0.dist-info/AUTHORS.rst
tsv2sqlite-0.5.0.dist-info/LICENSE
tsv2sqlite-0.5.0.dist-info/METADATA
tsv2sqlite-0.5.0.dist-info/WHEEL
tsv2sqlite-0.5.0.dist-info/entry_points.txt
tsv2sqlite-0.5.0.dist-info/top_level.txt
tsv2sqlite-0.5.0.dist-info/RECORD
