Metadata-Version: 2.1
Name: tsv2sqlite
Version: 0.5.0
Summary: Package for parsing a tab-delimited data file and loading the lines into SQLite3 database
Home-page: https://github.com/jai-python3/tsv2sqlite
Author: Jaideep Sundaram
Author-email: jai.python3@gmail.com
License: GNU General Public License v3
Keywords: tsv2sqlite
Classifier: Development Status :: 2 - Pre-Alpha
Classifier: Intended Audience :: Developers
Classifier: License :: OSI Approved :: GNU General Public License v3 (GPLv3)
Classifier: Natural Language :: English
Classifier: Programming Language :: Python :: 3
Classifier: Programming Language :: Python :: 3.6
Classifier: Programming Language :: Python :: 3.7
Classifier: Programming Language :: Python :: 3.8
Requires-Python: >=3.6
License-File: LICENSE
License-File: AUTHORS.rst
Requires-Dist: Click >=7.0
Requires-Dist: Rich
Requires-Dist: PyYAML
